LICENSE
MANIFEST.in
README.md
doc-requirements.txt
requirements.txt
setup.cfg
setup.py
test-requirements.txt
versioneer.py
rnbgrader/__init__.py
rnbgrader/_version.py
rnbgrader/allow_raise.py
rnbgrader/answers.py
rnbgrader/chunkrunner.py
rnbgrader/execheck.py
rnbgrader/grader.py
rnbgrader/grids.py
rnbgrader/kernels.py
rnbgrader/nbparser.py
rnbgrader/tmpdirs.py
rnbgrader.egg-info/PKG-INFO
rnbgrader.egg-info/SOURCES.txt
rnbgrader.egg-info/dependency_links.txt
rnbgrader.egg-info/entry_points.txt
rnbgrader.egg-info/requires.txt
rnbgrader.egg-info/top_level.txt
rnbgrader/tests/__init__.py
rnbgrader/tests/test_allow_raise.py
rnbgrader/tests/test_answers.py
rnbgrader/tests/test_chunkrunner.py
rnbgrader/tests/test_execheck.py
rnbgrader/tests/test_grader.py
rnbgrader/tests/test_grids.py
rnbgrader/tests/test_kernels.py
rnbgrader/tests/test_nbparser.py
rnbgrader/tests/test_py_grader.py
rnbgrader/tests/test_tmpdirs.py
rnbgrader/tests/data/.gitignore
rnbgrader/tests/data/allow_raise_in.Rmd
rnbgrader/tests/data/allow_raise_out.Rmd
rnbgrader/tests/data/cars.csv
rnbgrader/tests/data/chunk_options.Rmd
rnbgrader/tests/data/default.Rmd
rnbgrader/tests/data/list_chunk.Rmd
rnbgrader/tests/data/not_solution.Rmd
rnbgrader/tests/data/py_solution.Rmd
rnbgrader/tests/data/py_solution.ipynb
rnbgrader/tests/data/solution.Rmd
rnbgrader/tests/data/test_submissions/brettmatthew_139741_6519327_some_name.Rmd
rnbgrader/tests/data/test_submissions/brettmatthew_139741_6519328_another_name.Rmd
rnbgrader/tests/data/test_submissions2/brettmatthew_139741_6519327_some_name.Rmd
rnbgrader/tests/data/test_submissions2/rodriguezvalia_140801_6518299_notebook.rmd
rnbgrader/tests/data/test_submissions_markup/brettmatthew_139741_6519327_some_name.Rmd
rnbgrader/tests/data/test_submissions_markup/rodriguezvalia_140801_6518299_notebook.rmd