Metadata-Version: 2.1
Name: rnbgrader
Version: 0.3.4
Summary: Utilities for grading R Markdown notebook assignments
Home-page: http://github.com/matthew-brett/rnbgrader
Author: Matthew Brett
Author-email: matthew.brett@gmail.com
Maintainer: Matthew Brett
Maintainer-email: matthew.brett@gmail.com
License: BSD license
Classifier: Development Status :: 2 - Pre-Alpha
Classifier: Environment :: Console
Classifier: Intended Audience :: Developers
Classifier: Intended Audience :: Science/Research
Classifier: License :: OSI Approved :: BSD License
Classifier: Programming Language :: Python :: 3
Classifier: Programming Language :: Python :: 3.6
Classifier: Programming Language :: Python :: 3.7
Classifier: Programming Language :: Python :: 3.8
Classifier: Topic :: Scientific/Engineering
Classifier: Operating System :: Microsoft :: Windows
Classifier: Operating System :: POSIX
Classifier: Operating System :: Unix
Classifier: Operating System :: MacOS
Requires-Python: >=3.6
License-File: LICENSE
Requires-Dist: numpy>=1.12.0
Requires-Dist: pandas>=0.23
Requires-Dist: Pillow
Requires-Dist: pypandoc
Requires-Dist: jupyter_client>=5.0.0
Requires-Dist: tornado
Requires-Dist: gradools
Requires-Dist: ipykernel
Requires-Dist: jupytext
Requires-Dist: nbconvert
Requires-Dist: gradools
Provides-Extra: test
Requires-Dist: pytest; extra == "test"
Requires-Dist: matplotlib; extra == "test"
